[
      {
        "fromTime": "2022-02-02T00:00:00+01:00",
        "toTime": "2022-02-02T01:00:00+01:00",
        "value": 8.9,
        "qualityControlled": true,
        "index": 1,
        "color": "6ee86e"
      },
      {
        "fromTime": "2022-02-02T01:00:00+01:00",
        "toTime": "2022-02-02T02:00:00+01:00",
        "value": 9,
        "qualityControlled": true,
        "index": 1,
        "color": "6ee86e"
      },
      {
        "fromTime": "2022-02-02T02:00:00+01:00",
        "toTime": "2022-02-02T03:00:00+01:00",
        "value": 8.9,
        "qualityControlled": true,
        "index": 1,
        "color": "6ee86e"
      },
      {
        "fromTime": "2022-02-02T03:00:00+01:00",
        "toTime": "2022-02-02T04:00:00+01:00",
        "value": 12.9,
        "qualityControlled": true,
        "index": 1,
        "color": "6ee86e"
      },
      {
        "fromTime": "2022-02-02T04:00:00+01:00",
        "toTime": "2022-02-02T05:00:00+01:00",
        "value": 12.3,
        "qualityControlled": true,
        "index": 1,
        "color": "6ee86e"
      },
      {
        "fromTime": "2022-02-02T05:00:00+01:00",
        "toTime": "2022-02-02T06:00:00+01:00",
        "value": 16.2,
        "qualityControlled": true,
        "index": 1,
        "color": "6ee86e"
      },
      {
        "fromTime": "2022-02-02T06:00:00+01:00",
        "toTime": "2022-02-02T07:00:00+01:00",
        "value": 34.1,
        "qualityControlled": true,
        "index": 1,
        "color": "6ee86e"
      },
      {
        "fromTime": "2022-02-02T07:00:00+01:00",
        "toTime": "2022-02-02T08:00:00+01:00",
        "value": 27.2,
        "qualityControlled": true,
        "index": 1,
        "color": "6ee86e"
      },
      {
        "fromTime": "2022-02-02T08:00:00+01:00",
        "toTime": "2022-02-02T09:00:00+01:00",
        "value": 21.4,
        "qualityControlled": true,
        "index": 1,
        "color": "6ee86e"
      },
      {
        "fromTime": "2022-02-02T09:00:00+01:00",
        "toTime": "2022-02-02T10:00:00+01:00",
        "value": 34,
        "qualityControlled": true,
        "index": 1,
        "color": "6ee86e"
      },
      {
        "fromTime": "2022-02-02T10:00:00+01:00",
        "toTime": "2022-02-02T11:00:00+01:00",
        "value": 30.2,
        "qualityControlled": true,
        "index": 1,
        "color": "6ee86e"
      },
      {
        "fromTime": "2022-02-02T11:00:00+01:00",
        "toTime": "2022-02-02T12:00:00+01:00",
        "value": 25.1,
        "qualityControlled": true,
        "index": 1,
        "color": "6ee86e"
      },
      {
        "fromTime": "2022-02-02T12:00:00+01:00",
        "toTime": "2022-02-02T13:00:00+01:00",
        "value": 25,
        "qualityControlled": true,
        "index": 1,
        "color": "6ee86e"
      },
      {
        "fromTime": "2022-02-02T13:00:00+01:00",
        "toTime": "2022-02-02T14:00:00+01:00",
        "value": 26.3,
        "qualityControlled": true,
        "index": 1,
        "color": "6ee86e"
      },
      {
        "fromTime": "2022-02-02T14:00:00+01:00",
        "toTime": "2022-02-02T15:00:00+01:00",
        "value": 26.7,
        "qualityControlled": true,
        "index": 1,
        "color": "6ee86e"
      },
      {
        "fromTime": "2022-02-02T15:00:00+01:00",
        "toTime": "2022-02-02T16:00:00+01:00",
        "value": 20.1,
        "qualityControlled": true,
        "index": 1,
        "color": "6ee86e"
      },
      {
        "fromTime": "2022-02-02T16:00:00+01:00",
        "toTime": "2022-02-02T17:00:00+01:00",
        "value": 28.2,
        "qualityControlled": true,
        "index": 1,
        "color": "6ee86e"
      },
      {
        "fromTime": "2022-02-02T17:00:00+01:00",
        "toTime": "2022-02-02T18:00:00+01:00",
        "value": 58,
        "qualityControlled": true,
        "index": 1,
        "color": "6ee86e"
      },
      {
        "fromTime": "2022-02-02T18:00:00+01:00",
        "toTime": "2022-02-02T19:00:00+01:00",
        "value": 94.6,
        "qualityControlled": true,
        "index": 2,
        "color": "ff9900"
      },
      {
        "fromTime": "2022-02-02T19:00:00+01:00",
        "toTime": "2022-02-02T20:00:00+01:00",
        "value": 101,
        "qualityControlled": true,
        "index": 2,
        "color": "ff9900"
      },
      {
        "fromTime": "2022-02-02T20:00:00+01:00",
        "toTime": "2022-02-02T21:00:00+01:00",
        "value": 128.6,
        "qualityControlled": true,
        "index": 3,
        "color": "ff0000"
      },
      {
        "fromTime": "2022-02-02T21:00:00+01:00",
        "toTime": "2022-02-02T22:00:00+01:00",
        "value": 109,
        "qualityControlled": true,
        "index": 2,
        "color": "ff9900"
      },
      {
        "fromTime": "2022-02-02T22:00:00+01:00",
        "toTime": "2022-02-02T23:00:00+01:00",
        "value": 93.7,
        "qualityControlled": true,
        "index": 2,
        "color": "ff9900"
      },
      {
        "fromTime": "2022-02-02T23:00:00+01:00",
        "toTime": "2022-02-03T00:00:00+01:00",
        "value": 71.6,
        "qualityControlled": true,
        "index": 2,
        "color": "ff9900"
      }
    ]